Workbook
Name Slicer_Category: #N/A
Name Slicer_Category1: #N/A
Name Slicer_Months__OrderDate: #N/A
Name Slicer_Months__OrderDate1: #N/A
Name Slicer_Region: #N/A
Name Slicer_Segment: #N/A
Name Slicer_Segment1: #N/A

Sheet Raw Data
A1: OrderID | B1: OrderDate | C1: CustomerID | D1: CustomerName | E1: Segment | F1: Region | G1: ProductID | H1: ProductName | I1: Category | J1: Quantity | K1: UnitPrice | L1: Discount | M1: Sales | N1: Profit | O1: ShippingCost | P1: PaymentMethod
A2: ORD-1001 | B2: 45321 | C2: CUST-0070 | D2: Arjun Kapoor | E2: Consumer | F2: East | G2: ELE-06 | H2: Noise Cancelling Headphones | I2: Electronics | J2: 1 | K2: 2878.29 | L2: 0.1 | M2: 2590.46 | N2: 345.83 | O2: 142.16 | P2: Credit Card
A3: ORD-1002 | B3: 45327 | C3: CUST-0066 | D3: Aadhya Mehta | E3: Home Office | F3: North | G3: ELE-03 | H3: USB-C Charger | I3: Electronics | J3: 10 | K3: 865.05 | L3: 0.2 | M3: 6920.4 | N3: 1653.97 | O3: 47.57 | P3: Cash on Delivery
A4: ORD-1003 | B4: 45312 | C4: CUST-0032 | D4: Ayaan Kumar | E4: Home Office | F4: West | G4: HOM-10 | H4: Table Lamp | I4: Home & Kitchen | J4: 10 | K4: 777.12 | L4: 0.15 | M4: 6605.52 | N4: 1197.4 | O4: 140.24 | P4: UPI
A5: ORD-1004 | B5: 45427 | C5: CUST-0027 | D5: Ethan Khan | E5: Consumer | F5: West | G5: OFF-04 | H5: Ball Pen Box | I5: Office Supplies | J5: 7 | K5: 148.16 | L5: 0.15 | M5: 881.55 | N5: 233.35 | O5: 92.72 | P5: Credit Card
A6: ORD-1005 | B6: 45580 | C6: CUST-0002 | D6: Ayaan Nair | E6: Consumer | F6: North | G6: CLO-10 | H6: Woolen Sweater | I6: Clothing | J6: 2 | K6: 461.17 | L6: 0 | M6: 922.34 | N6: 298.4 | O6: 50.47 | P6: UPI
A7: ORD-1006 | B7: 45437 | C7: CUST-0009 | D7: Ananya Iyer | E7: Consumer | F7: South | G7: FUR-06 | H7: Standing Desk | I7: Furniture | J7: 3 | K7: 4617.84 | L7: 0.1 | M7: 12468.17 | N7: 2412.11 | O7: 160.69 | P7: Cash on Delivery
A8: ORD-1007 | B8: 45631 | C8: CUST-0002 | D8: Ayaan Nair | E8: Consumer | F8: North | G8: HOM-05 | H8: Water Bottle | I8: Home & Kitchen | J8: 2 | K8: 4719.08 | L8: 0 | M8: 9438.16 | N8: 3623.15 | O8: 224.63 | P8: Cash on Delivery
A9: ORD-1008 | B9: 45601 | C9: CUST-0020 | D9: Diya Reddy | E9: Home Office | F9: East | G9: OFF-05 | H9: File Folder | I9: Office Supplies | J9: 4 | K9: 588.21 | L9: 0 | M9: 2352.84 | N9: 654.39 | O9: 216.17 | P9: Cash on Delivery
A10: ORD-1009 | B10: 45339 | C10: CUST-0063 | D10: Pari Smith | E10: Consumer | F10: West | G10: OFF-01 | H10: A4 Paper Ream | I10: Office Supplies | J10: 11 | K10: 367.68 | L10: 0 | M10: 4044.48 | N10: 1775.44 | O10: 96.72 | P10: Debit Card
A11: ORD-1010 | B11: 45574 | C11: CUST-0034 | D11: James Patel | E11: Home Office | F11: West | G11: FUR-08 | H11: Bed Frame | I11: Furniture | J11: 12 | K11: 4535.96 | L11: 0 | M11: 54431.52 | N11: 22971.82 | O11: 237.36 | P11: Debit Card
A12: ORD-1011 | B12: 45590 | C12: CUST-0070 | D12: Arjun Kapoor | E12: Consumer | F12: East | G12: ELE-06 | H12: Noise Cancelling Headphones | I12: Electronics | J12: 9 | K12: 1177.57 | L12: 0 | M12: 10598.13 | N12: 4658.33 | O12: 103.87 | P12: Credit Card
A13: ORD-1012 | B13: 45633 | C13: CUST-0046 | D13: Myra Sharma | E13: Consumer | F13: East | G13: FUR-04 | H13: Bean Bag | I13: Furniture | J13: 2 | K13: 3958.69 | L13: 0.1 | M13: 7125.64 | N13: 1021.07 | O13: 113.47 | P13: Cash on Delivery
... A421: ORD-1420 | B421: 45511 | C421: CUST-0016 | D421: Liam Gupta | E421: Consumer | F421: South | G421: CLO-01 | H421: Cotton T-Shirt | I421: Clothing | J421: 5 | K421: 1524.52 | L421: 0 | M421: 7622.6 | N421: 3123.5 | O421: 214.58 | P421: Credit Card

Sheet Dashboard
A1: SALES PERFORMANCE DASHBOARD — FY2024
B3: Total Sales | E3: Total Profit | H3: Total Orders
B4: =SUM('Raw Data'!M2:M421) -> 5800375.9 | E4: =SUM('Raw Data'!N2:N421) -> 1656165.6 | H4: =COUNTA('Raw Data'!A2:A421) -> 420
B7: Avg Order Value | E7: Unique Customers | H7: Profit Margin %
B8: =B4/H4 -> 13810.419 | E8: =SUMPRODUCT(1/COUNTIF('Raw Data'!C2:C421,'Raw Data'!C2:C421)) -> 80 | H8: =E4/B4 -> 0.28552728
A11: Charts below are built from the Product Analysis, Customer Analysis, and Time Analysis sheets.

Sheet Time Analysis
A1: TIME & PAYMENT ANALYSIS
A3: Monthly Sales Trend (2024)
A4: Month | B4: Total Sales | C4: Total Profit | D4: Order Count
A5: Jan-2024 | B5: =SUMPRODUCT(('Raw Data'!$B$2:$B$421>=DATE(2024,1,1))*('Raw Data'!$B$2:$B$421<DATE(2024,2,1)*(1))*'Raw Data'!$M$2:$M$421) -> 489471.15 | C5: =SUMPRODUCT(('Raw Data'!$B$2:$B$421>=DATE(2024,1,1))*('Raw Data'!$B$2:$B$421<DATE(2024,2,1))*'Raw Data'!$N$2:$N$421) -> 143184.67 | D5: =SUMPRODUCT(('Raw Data'!$B$2:$B$421>=DATE(2024,1,1))*('Raw Data'!$B$2:$B$421<DATE(2024,2,1))) -> 33
A6: Feb-2024 | B6: =SUMPRODUCT(('Raw Data'!$B$2:$B$421>=DATE(2024,2,1))*('Raw Data'!$B$2:$B$421<DATE(2024,3,1)*(1))*'Raw Data'!$M$2:$M$421) -> 360307.13 | C6: =SUMPRODUCT(('Raw Data'!$B$2:$B$421>=DATE(2024,2,1))*('Raw Data'!$B$2:$B$421<DATE(2024,3,1))*'Raw Data'!$N$2:$N$421) -> 100822.97 | D6: =SUMPRODUCT(('Raw Data'!$B$2:$B$421>=DATE(2024,2,1))*('Raw Data'!$B$2:$B$421<DATE(2024,3,1))) -> 32
A7: Mar-2024 | B7: =SUMPRODUCT(('Raw Data'!$B$2:$B$421>=DATE(2024,3,1))*('Raw Data'!$B$2:$B$421<DATE(2024,4,1)*(1))*'Raw Data'!$M$2:$M$421) -> 786759.57 | C7: =SUMPRODUCT(('Raw Data'!$B$2:$B$421>=DATE(2024,3,1))*('Raw Data'!$B$2:$B$421<DATE(2024,4,1))*'Raw Data'!$N$2:$N$421) -> 239888.87 | D7: =SUMPRODUCT(('Raw Data'!$B$2:$B$421>=DATE(2024,3,1))*('Raw Data'!$B$2:$B$421<DATE(2024,4,1))) -> 39
A8: Apr-2024 | B8: =SUMPRODUCT(('Raw Data'!$B$2:$B$421>=DATE(2024,4,1))*('Raw Data'!$B$2:$B$421<DATE(2024,5,1)*(1))*'Raw Data'!$M$2:$M$421) -> 507548.51 | C8: =SUMPRODUCT(('Raw Data'!$B$2:$B$421>=DATE(2024,4,1))*('Raw Data'!$B$2:$B$421<DATE(2024,5,1))*'Raw Data'!$N$2:$N$421) -> 160326.79 | D8: =SUMPRODUCT(('Raw Data'!$B$2:$B$421>=DATE(2024,4,1))*('Raw Data'!$B$2:$B$421<DATE(2024,5,1))) -> 36
A9: May-2024 | B9: =SUMPRODUCT(('Raw Data'!$B$2:$B$421>=DATE(2024,5,1))*('Raw Data'!$B$2:$B$421<DATE(2024,6,1)*(1))*'Raw Data'!$M$2:$M$421) -> 425565.43 | C9: =SUMPRODUCT(('Raw Data'!$B$2:$B$421>=DATE(2024,5,1))*('Raw Data'!$B$2:$B$421<DATE(2024,6,1))*'Raw Data'!$N$2:$N$421) -> 114183.99 | D9: =SUMPRODUCT(('Raw Data'!$B$2:$B$421>=DATE(2024,5,1))*('Raw Data'!$B$2:$B$421<DATE(2024,6,1))) -> 35
A10: Jun-2024 | B10: =SUMPRODUCT(('Raw Data'!$B$2:$B$421>=DATE(2024,6,1))*('Raw Data'!$B$2:$B$421<DATE(2024,7,1)*(1))*'Raw Data'!$M$2:$M$421) -> 543259.01 | C10: =SUMPRODUCT(('Raw Data'!$B$2:$B$421>=DATE(2024,6,1))*('Raw Data'!$B$2:$B$421<DATE(2024,7,1))*'Raw Data'!$N$2:$N$421) -> 151583.37 | D10: =SUMPRODUCT(('Raw Data'!$B$2:$B$421>=DATE(2024,6,1))*('Raw Data'!$B$2:$B$421<DATE(2024,7,1))) -> 38
A11: Jul-2024 | B11: =SUMPRODUCT(('Raw Data'!$B$2:$B$421>=DATE(2024,7,1))*('Raw Data'!$B$2:$B$421<DATE(2024,8,1)*(1))*'Raw Data'!$M$2:$M$421) -> 286633 | C11: =SUMPRODUCT(('Raw Data'!$B$2:$B$421>=DATE(2024,7,1))*('Raw Data'!$B$2:$B$421<DATE(2024,8,1))*'Raw Data'!$N$2:$N$421) -> 71601.46 | D11: =SUMPRODUCT(('Raw Data'!$B$2:$B$421>=DATE(2024,7,1))*('Raw Data'!$B$2:$B$421<DATE(2024,8,1))) -> 26
A12: Aug-2024 | B12: =SUMPRODUCT(('Raw Data'!$B$2:$B$421>=DATE(2024,8,1))*('Raw Data'!$B$2:$B$421<DATE(2024,9,1)*(1))*'Raw Data'!$M$2:$M$421) -> 359755.51 | C12: =SUMPRODUCT(('Raw Data'!$B$2:$B$421>=DATE(2024,8,1))*('Raw Data'!$B$2:$B$421<DATE(2024,9,1))*'Raw Data'!$N$2:$N$421) -> 107678 | D12: =SUMPRODUCT(('Raw Data'!$B$2:$B$421>=DATE(2024,8,1))*('Raw Data'!$B$2:$B$421<DATE(2024,9,1))) -> 33
A13: Sep-2024 | B13: =SUMPRODUCT(('Raw Data'!$B$2:$B$421>=DATE(2024,9,1))*('Raw Data'!$B$2:$B$421<DATE(2024,10,1)*(1))*'Raw Data'!$M$2:$M$421) -> 534174.02 | C13: =SUMPRODUCT(('Raw Data'!$B$2:$B$421>=DATE(2024,9,1))*('Raw Data'!$B$2:$B$421<DATE(2024,10,1))*'Raw Data'!$N$2:$N$421) -> 141254.6 | D13: =SUMPRODUCT(('Raw Data'!$B$2:$B$421>=DATE(2024,9,1))*('Raw Data'!$B$2:$B$421<DATE(2024,10,1))) -> 32
A14: Oct-2024 | B14: =SUMPRODUCT(('Raw Data'!$B$2:$B$421>=DATE(2024,10,1))*('Raw Data'!$B$2:$B$421<DATE(2024,11,1)*(1))*'Raw Data'!$M$2:$M$421) -> 447535.92 | C14: =SUMPRODUCT(('Raw Data'!$B$2:$B$421>=DATE(2024,10,1))*('Raw Data'!$B$2:$B$421<DATE(2024,11,1))*'Raw Data'!$N$2:$N$421) -> 122887.89 | D14: =SUMPRODUCT(('Raw Data'!$B$2:$B$421>=DATE(2024,10,1))*('Raw Data'!$B$2:$B$421<DATE(2024,11,1))) -> 37
A15: Nov-2024 | B15: =SUMPRODUCT(('Raw Data'!$B$2:$B$421>=DATE(2024,11,1))*('Raw Data'!$B$2:$B$421<DATE(2024,12,1)*(1))*'Raw Data'!$M$2:$M$421) -> 372943.95 | C15: =SUMPRODUCT(('Raw Data'!$B$2:$B$421>=DATE(2024,11,1))*('Raw Data'!$B$2:$B$421<DATE(2024,12,1))*'Raw Data'!$N$2:$N$421) -> 113921.31 | D15: =SUMPRODUCT(('Raw Data'!$B$2:$B$421>=DATE(2024,11,1))*('Raw Data'!$B$2:$B$421<DATE(2024,12,1))) -> 30
A16: Dec-2024 | B16: =SUMPRODUCT(('Raw Data'!$B$2:$B$421>=DATE(2024,12,1))*('Raw Data'!$B$2:$B$421<DATE(2025,1,1))*'Raw Data'!$M$2:$M$421) -> 686422.73 | C16: =SUMPRODUCT(('Raw Data'!$B$2:$B$421>=DATE(2024,12,1))*('Raw Data'!$B$2:$B$421<DATE(2025,1,1))*'Raw Data'!$N$2:$N$421) -> 188831.66 | D16: =SUMPRODUCT(('Raw Data'!$B$2:$B$421>=DATE(2024,12,1))*('Raw Data'!$B$2:$B$421<DATE(2025,1,1))) -> 49
A19: Payment Method Summary
A20: Payment Method | B20: Total Sales | C20: Order Count | D20: % of Total Orders
A21: Credit Card | B21: =SUMIFS('Raw Data'!$M$2:$M$421,'Raw Data'!$P$2:$P$421,A21) -> 1031084.7 | C21: =COUNTIFS('Raw Data'!$P$2:$P$421,A21) -> 75 | D21: =IFERROR(C21/420,0) -> 0.17857143
A22: Debit Card | B22: =SUMIFS('Raw Data'!$M$2:$M$421,'Raw Data'!$P$2:$P$421,A22) -> 1107207.9 | C22: =COUNTIFS('Raw Data'!$P$2:$P$421,A22) -> 74 | D22: =IFERROR(C22/420,0) -> 0.17619048
A23: UPI | B23: =SUMIFS('Raw Data'!$M$2:$M$421,'Raw Data'!$P$2:$P$421,A23) -> 1184810.1 | C23: =COUNTIFS('Raw Data'!$P$2:$P$421,A23) -> 88 | D23: =IFERROR(C23/420,0) -> 0.20952381
A24: Net Banking | B24: =SUMIFS('Raw Data'!$M$2:$M$421,'Raw Data'!$P$2:$P$421,A24) -> 1115719.2 | C24: =COUNTIFS('Raw Data'!$P$2:$P$421,A24) -> 85 | D24: =IFERROR(C24/420,0) -> 0.20238095
A25: Cash on Delivery | B25: =SUMIFS('Raw Data'!$M$2:$M$421,'Raw Data'!$P$2:$P$421,A25) -> 1361554 | C25: =COUNTIFS('Raw Data'!$P$2:$P$421,A25) -> 98 | D25: =IFERROR(C25/420,0) -> 0.23333333

Sheet Customer Analysis
A1: CUSTOMER-BASED ANALYSIS
A3: Segment Summary
A4: Segment | B4: Total Sales | C4: Total Profit | D4: Order Count | E4: Unique Customers | F4: Avg Order Value
A5: Consumer | B5: =SUMIFS('Raw Data'!$M$2:$M$421,'Raw Data'!$E$2:$E$421,A5) -> 3110524.2 | C5: =SUMIFS('Raw Data'!$N$2:$N$421,'Raw Data'!$E$2:$E$421,A5) -> 873137.25 | D5: =COUNTIFS('Raw Data'!$E$2:$E$421,A5) -> 225 | E5: =SUMPRODUCT(('Raw Data'!$E$2:$E$421=A5)/COUNTIFS('Raw Data'!$C$2:$C$421,'Raw Data'!$C$2:$C$421&"")) -> 41 | F5: =IFERROR(B5/D5,0) -> 13824.552
A6: Corporate | B6: =SUMIFS('Raw Data'!$M$2:$M$421,'Raw Data'!$E$2:$E$421,A6) -> 1374137.6 | C6: =SUMIFS('Raw Data'!$N$2:$N$421,'Raw Data'!$E$2:$E$421,A6) -> 383525.65 | D6: =COUNTIFS('Raw Data'!$E$2:$E$421,A6) -> 90 | E6: =SUMPRODUCT(('Raw Data'!$E$2:$E$421=A6)/COUNTIFS('Raw Data'!$C$2:$C$421,'Raw Data'!$C$2:$C$421&"")) -> 17 | F6: =IFERROR(B6/D6,0) -> 15268.195
A7: Home Office | B7: =SUMIFS('Raw Data'!$M$2:$M$421,'Raw Data'!$E$2:$E$421,A7) -> 1315714.2 | C7: =SUMIFS('Raw Data'!$N$2:$N$421,'Raw Data'!$E$2:$E$421,A7) -> 399502.68 | D7: =COUNTIFS('Raw Data'!$E$2:$E$421,A7) -> 105 | E7: =SUMPRODUCT(('Raw Data'!$E$2:$E$421=A7)/COUNTIFS('Raw Data'!$C$2:$C$421,'Raw Data'!$C$2:$C$421&"")) -> 22 | F7: =IFERROR(B7/D7,0) -> 12530.611
A10: Region Summary
A11: Region | B11: Total Sales | C11: Total Profit | D11: Order Count | E11: Avg Discount %
A12: North | B12: =SUMIFS('Raw Data'!$M$2:$M$421,'Raw Data'!$F$2:$F$421,A12) -> 1068826.7 | C12: =SUMIFS('Raw Data'!$N$2:$N$421,'Raw Data'!$F$2:$F$421,A12) -> 320525.12 | D12: =COUNTIFS('Raw Data'!$F$2:$F$421,A12) -> 83 | E12: =AVERAGEIFS('Raw Data'!$L$2:$L$421,'Raw Data'!$F$2:$F$421,A12) -> 0.064457831
A13: South | B13: =SUMIFS('Raw Data'!$M$2:$M$421,'Raw Data'!$F$2:$F$421,A13) -> 868560.04 | C13: =SUMIFS('Raw Data'!$N$2:$N$421,'Raw Data'!$F$2:$F$421,A13) -> 240178.68 | D13: =COUNTIFS('Raw Data'!$F$2:$F$421,A13) -> 59 | E13: =AVERAGEIFS('Raw Data'!$L$2:$L$421,'Raw Data'!$F$2:$F$421,A13) -> 0.077966102
A14: East | B14: =SUMIFS('Raw Data'!$M$2:$M$421,'Raw Data'!$F$2:$F$421,A14) -> 1147516.3 | C14: =SUMIFS('Raw Data'!$N$2:$N$421,'Raw Data'!$F$2:$F$421,A14) -> 328285.21 | D14: =COUNTIFS('Raw Data'!$F$2:$F$421,A14) -> 85 | E14: =AVERAGEIFS('Raw Data'!$L$2:$L$421,'Raw Data'!$F$2:$F$421,A14) -> 0.061764706
A15: West | B15: =SUMIFS('Raw Data'!$M$2:$M$421,'Raw Data'!$F$2:$F$421,A15) -> 1453113.7 | C15: =SUMIFS('Raw Data'!$N$2:$N$421,'Raw Data'!$F$2:$F$421,A15) -> 393107.85 | D15: =COUNTIFS('Raw Data'!$F$2:$F$421,A15) -> 100 | E15: =AVERAGEIFS('Raw Data'!$L$2:$L$421,'Raw Data'!$F$2:$F$421,A15) -> 0.083
A16: Central | B16: =SUMIFS('Raw Data'!$M$2:$M$421,'Raw Data'!$F$2:$F$421,A16) -> 1262359.1 | C16: =SUMIFS('Raw Data'!$N$2:$N$421,'Raw Data'!$F$2:$F$421,A16) -> 374068.72 | D16: =COUNTIFS('Raw Data'!$F$2:$F$421,A16) -> 93 | E16: =AVERAGEIFS('Raw Data'!$L$2:$L$421,'Raw Data'!$F$2:$F$421,A16) -> 0.079569892
A19: Top 10 Customers by Sales
A20: Rank | B20: Customer Name | C20: Segment | D20: Region | E20: Total Sales | F20: Orders Placed | G20: Avg Order Value
A21: 1 | B21: Vihaan Das | C21: Corporate | D21: South | E21: =SUMIFS('Raw Data'!$M$2:$M$421,'Raw Data'!$D$2:$D$421,B21) -> 413327.94 | F21: =COUNTIFS('Raw Data'!$D$2:$D$421,B21) -> 18 | G21: =IFERROR(E21/F21,0) -> 22962.663
A22: 2 | B22: Liam Das | C22: Corporate | D22: East | E22: =SUMIFS('Raw Data'!$M$2:$M$421,'Raw Data'!$D$2:$D$421,B22) -> 201621.7 | F22: =COUNTIFS('Raw Data'!$D$2:$D$421,B22) -> 8 | G22: =IFERROR(E22/F22,0) -> 25202.713
A23: 3 | B23: Olivia Smith | C23: Consumer | D23: Central | E23: =SUMIFS('Raw Data'!$M$2:$M$421,'Raw Data'!$D$2:$D$421,B23) -> 186309.85 | F23: =COUNTIFS('Raw Data'!$D$2:$D$421,B23) -> 6 | G23: =IFERROR(E23/F23,0) -> 31051.642
A24: 4 | B24: Reyansh Brown | C24: Consumer | D24: Central | E24: =SUMIFS('Raw Data'!$M$2:$M$421,'Raw Data'!$D$2:$D$421,B24) -> 185040.5 | F24: =COUNTIFS('Raw Data'!$D$2:$D$421,B24) -> 8 | G24: =IFERROR(E24/F24,0) -> 23130.062
A25: 5 | B25: Anika Patel | C25: Home Office | D25: North | E25: =SUMIFS('Raw Data'!$M$2:$M$421,'Raw Data'!$D$2:$D$421,B25) -> 164327.91 | F25: =COUNTIFS('Raw Data'!$D$2:$D$421,B25) -> 7 | G25: =IFERROR(E25/F25,0) -> 23475.416
A26: 6 | B26: Arjun Kapoor | C26: Consumer | D26: East | E26: =SUMIFS('Raw Data'!$M$2:$M$421,'Raw Data'!$D$2:$D$421,B26) -> 161449.92 | F26: =COUNTIFS('Raw Data'!$D$2:$D$421,B26) -> 11 | G26: =IFERROR(E26/F26,0) -> 14677.265
A27: 7 | B27: Navya Nair | C27: Consumer | D27: West | E27: =SUMIFS('Raw Data'!$M$2:$M$421,'Raw Data'!$D$2:$D$421,B27) -> 156368.39 | F27: =COUNTIFS('Raw Data'!$D$2:$D$421,B27) -> 9 | G27: =IFERROR(E27/F27,0) -> 17374.266
A28: 8 | B28: Isabella Sharma | C28: Home Office | D28: East | E28: =SUMIFS('Raw Data'!$M$2:$M$421,'Raw Data'!$D$2:$D$421,B28) -> 155344.72 | F28: =COUNTIFS('Raw Data'!$D$2:$D$421,B28) -> 8 | G28: =IFERROR(E28/F28,0) -> 19418.09
A29: 9 | B29: Riya Iyer | C29: Consumer | D29: West | E29: =SUMIFS('Raw Data'!$M$2:$M$421,'Raw Data'!$D$2:$D$421,B29) -> 144391.63 | F29: =COUNTIFS('Raw Data'!$D$2:$D$421,B29) -> 12 | G29: =IFERROR(E29/F29,0) -> 12032.636
A30: 10 | B30: Kiara Johnson | C30: Corporate | D30: North | E30: =SUMIFS('Raw Data'!$M$2:$M$421,'Raw Data'!$D$2:$D$421,B30) -> 136136.3 | F30: =COUNTIFS('Raw Data'!$D$2:$D$421,B30) -> 7 | G30: =IFERROR(E30/F30,0) -> 19448.043

Sheet Customer pivot
A2: Row Labels | B2: Sum of Sales
A3: Vihaan Das | B3: 413327.94
A4: Liam Das | B4: 201621.7
A5: Olivia Smith | B5: 186309.85
A6: Reyansh Brown | B6: 185040.5
A7: Anika Patel | B7: 164327.91
A8: Arjun Kapoor | B8: 161449.92
A9: Navya Nair | B9: 156368.39
A10: Isabella Sharma | B10: 155344.72
A11: Riya Iyer | B11: 144391.63
A12: Kiara Johnson | B12: 136136.3
A14: Row Labels | B14: Count of CustomerName | D14: Row Labels | E14: Count of CustomerName
A15: Central | B15: 93 | D15: Jan | E15: 33 | G15: Row Labels | H15: Count of CustomerName
A16: East | B16: 85 | D16: Feb | E16: 32 | G16: Central | H16: 93
A17: North | B17: 83 | D17: Mar | E17: 39 | G17: Consumer | H17: 41
A18: South | B18: 59 | D18: Apr | E18: 36 | G18: Corporate | H18: 9
A19: West | B19: 100 | D19: May | E19: 35 | G19: Home Office | H19: 43
D20: Jun | E20: 38 | G20: East | H20: 85
A21: Row Labels | B21: Count of CustomerName | D21: Jul | E21: 26 | G21: Consumer | H21: 34
A22: Consumer | B22: 225 | D22: Aug | E22: 33 | G22: Corporate | H22: 29
A23: Corporate | B23: 90 | D23: Sep | E23: 32 | G23: Home Office | H23: 22
A24: Home Office | B24: 105 | D24: Oct | E24: 37 | G24: North | H24: 83
D25: Nov | E25: 30 | G25: Consumer | H25: 46
A26: Row Labels | B26: Count of CustomerName | D26: Dec | E26: 49 | G26: Corporate | H26: 16
A27: Cash on Delivery | B27: 98 | G27: Home Office | H27: 21
A28: Credit Card | B28: 75 | G28: South | H28: 59
A29: Debit Card | B29: 74 | G29: Consumer | H29: 31
A30: Net Banking | B30: 85 | G30: Corporate | H30: 19
A31: UPI | B31: 88 | G31: Home Office | H31: 9
G32: West | H32: 100
G33: Consumer | H33: 73
G34: Corporate | H34: 17
G35: Home Office | H35: 10

Sheet Customer Dashboard

Sheet Product Analysis
A1: PRODUCT-BASED ANALYSIS
A3: Category Summary
A4: Category | B4: Total Sales | C4: Total Profit | D4: Profit Margin % | E4: Units Sold | F4: Order Count | G4: Avg Order Value
A5: Electronics | B5: =SUMIFS('Raw Data'!$M$2:$M$421,'Raw Data'!$I$2:$I$421,A5) -> 1079969 | C5: =SUMIFS('Raw Data'!$N$2:$N$421,'Raw Data'!$I$2:$I$421,A5) -> 286935.47 | D5: =IFERROR(C5/B5,0) -> 0.26568862 | E5: =SUMIFS('Raw Data'!$J$2:$J$421,'Raw Data'!$I$2:$I$421,A5) -> 496 | F5: =COUNTIFS('Raw Data'!$I$2:$I$421,A5) -> 75 | G5: =IFERROR(B5/F5,0) -> 14399.586
A6: Furniture | B6: =SUMIFS('Raw Data'!$M$2:$M$421,'Raw Data'!$I$2:$I$421,A6) -> 2174930.6 | C6: =SUMIFS('Raw Data'!$N$2:$N$421,'Raw Data'!$I$2:$I$421,A6) -> 687192.43 | D6: =IFERROR(C6/B6,0) -> 0.31596063 | E6: =SUMIFS('Raw Data'!$J$2:$J$421,'Raw Data'!$I$2:$I$421,A6) -> 439 | F6: =COUNTIFS('Raw Data'!$I$2:$I$421,A6) -> 68 | G6: =IFERROR(B6/F6,0) -> 31984.273
A7: Office Supplies | B7: =SUMIFS('Raw Data'!$M$2:$M$421,'Raw Data'!$I$2:$I$421,A7) -> 206437.1 | C7: =SUMIFS('Raw Data'!$N$2:$N$421,'Raw Data'!$I$2:$I$421,A7) -> 54896.72 | D7: =IFERROR(C7/B7,0) -> 0.26592468 | E7: =SUMIFS('Raw Data'!$J$2:$J$421,'Raw Data'!$I$2:$I$421,A7) -> 569 | F7: =COUNTIFS('Raw Data'!$I$2:$I$421,A7) -> 89 | G7: =IFERROR(B7/F7,0) -> 2319.518
A8: Clothing | B8: =SUMIFS('Raw Data'!$M$2:$M$421,'Raw Data'!$I$2:$I$421,A8) -> 775337.07 | C8: =SUMIFS('Raw Data'!$N$2:$N$421,'Raw Data'!$I$2:$I$421,A8) -> 211497.56 | D8: =IFERROR(C8/B8,0) -> 0.27278144 | E8: =SUMIFS('Raw Data'!$J$2:$J$421,'Raw Data'!$I$2:$I$421,A8) -> 625 | F8: =COUNTIFS('Raw Data'!$I$2:$I$421,A8) -> 95 | G8: =IFERROR(B8/F8,0) -> 8161.4428
A9: Home & Kitchen | B9: =SUMIFS('Raw Data'!$M$2:$M$421,'Raw Data'!$I$2:$I$421,A9) -> 1563702.2 | C9: =SUMIFS('Raw Data'!$N$2:$N$421,'Raw Data'!$I$2:$I$421,A9) -> 415643.4 | D9: =IFERROR(C9/B9,0) -> 0.26580726 | E9: =SUMIFS('Raw Data'!$J$2:$J$421,'Raw Data'!$I$2:$I$421,A9) -> 635 | F9: =COUNTIFS('Raw Data'!$I$2:$I$421,A9) -> 93 | G9: =IFERROR(B9/F9,0) -> 16814.002
A10: TOTAL | B10: =SUM(B5:B9) -> 5800375.9 | C10: =SUM(C5:C9) -> 1656165.6 | D10: =IFERROR(C10/B10,0) -> 0.28552728 | E10: =SUM(E5:E9) -> 2764 | F10: =SUM(F5:F9) -> 420 | G10: =IFERROR(B10/F10,0) -> 13810.419
A13: Top 10 Products by Sales
A14: Rank | B14: Product Name | C14: Category | D14: Total Sales | E14: Total Profit | F14: Units Sold
A15: 1 | B15: Bookshelf | C15: Furniture | D15: =SUMIFS('Raw Data'!$M$2:$M$421,'Raw Data'!$H$2:$H$421,B15) -> 355677.49 | E15: =SUMIFS('Raw Data'!$N$2:$N$421,'Raw Data'!$H$2:$H$421,B15) -> 103766.16 | F15: =SUMIFS('Raw Data'!$J$2:$J$421,'Raw Data'!$H$2:$H$421,B15) -> 68
A16: 2 | B16: Study Table | C16: Furniture | D16: =SUMIFS('Raw Data'!$M$2:$M$421,'Raw Data'!$H$2:$H$421,B16) -> 351751.69 | E16: =SUMIFS('Raw Data'!$N$2:$N$421,'Raw Data'!$H$2:$H$421,B16) -> 108670.84 | F16: =SUMIFS('Raw Data'!$J$2:$J$421,'Raw Data'!$H$2:$H$421,B16) -> 69
A17: 3 | B17: Bed Frame | C17: Furniture | D17: =SUMIFS('Raw Data'!$M$2:$M$421,'Raw Data'!$H$2:$H$421,B17) -> 312388.87 | E17: =SUMIFS('Raw Data'!$N$2:$N$421,'Raw Data'!$H$2:$H$421,B17) -> 101302.38 | F17: =SUMIFS('Raw Data'!$J$2:$J$421,'Raw Data'!$H$2:$H$421,B17) -> 65
A18: 4 | B18: Dinner Set | C18: Home & Kitchen | D18: =SUMIFS('Raw Data'!$M$2:$M$421,'Raw Data'!$H$2:$H$421,B18) -> 288886.33 | E18: =SUMIFS('Raw Data'!$N$2:$N$421,'Raw Data'!$H$2:$H$421,B18) -> 73931.95 | F18: =SUMIFS('Raw Data'!$J$2:$J$421,'Raw Data'!$H$2:$H$421,B18) -> 98
A19: 5 | B19: Vacuum Cleaner | C19: Home & Kitchen | D19: =SUMIFS('Raw Data'!$M$2:$M$421,'Raw Data'!$H$2:$H$421,B19) -> 282782.28 | E19: =SUMIFS('Raw Data'!$N$2:$N$421,'Raw Data'!$H$2:$H$421,B19) -> 60455.81 | F19: =SUMIFS('Raw Data'!$J$2:$J$421,'Raw Data'!$H$2:$H$421,B19) -> 81
A20: 6 | B20: Bean Bag | C20: Furniture | D20: =SUMIFS('Raw Data'!$M$2:$M$421,'Raw Data'!$H$2:$H$421,B20) -> 252725.73 | E20: =SUMIFS('Raw Data'!$N$2:$N$421,'Raw Data'!$H$2:$H$421,B20) -> 87561.26 | F20: =SUMIFS('Raw Data'!$J$2:$J$421,'Raw Data'!$H$2:$H$421,B20) -> 33
A21: 7 | B21: Office Chair | C21: Furniture | D21: =SUMIFS('Raw Data'!$M$2:$M$421,'Raw Data'!$H$2:$H$421,B21) -> 222020.05 | E21: =SUMIFS('Raw Data'!$N$2:$N$421,'Raw Data'!$H$2:$H$421,B21) -> 49048.82 | F21: =SUMIFS('Raw Data'!$J$2:$J$421,'Raw Data'!$H$2:$H$421,B21) -> 44
A22: 8 | B22: USB-C Charger | C22: Electronics | D22: =SUMIFS('Raw Data'!$M$2:$M$421,'Raw Data'!$H$2:$H$421,B22) -> 206299.55 | E22: =SUMIFS('Raw Data'!$N$2:$N$421,'Raw Data'!$H$2:$H$421,B22) -> 55026.03 | F22: =SUMIFS('Raw Data'!$J$2:$J$421,'Raw Data'!$H$2:$H$421,B22) -> 81
A23: 9 | B23: Table Lamp | C23: Home & Kitchen | D23: =SUMIFS('Raw Data'!$M$2:$M$421,'Raw Data'!$H$2:$H$421,B23) -> 200736.84 | E23: =SUMIFS('Raw Data'!$N$2:$N$421,'Raw Data'!$H$2:$H$421,B23) -> 60438.23 | F23: =SUMIFS('Raw Data'!$J$2:$J$421,'Raw Data'!$H$2:$H$421,B23) -> 104
A24: 10 | B24: Sofa Cover | C24: Furniture | D24: =SUMIFS('Raw Data'!$M$2:$M$421,'Raw Data'!$H$2:$H$421,B24) -> 198090.86 | E24: =SUMIFS('Raw Data'!$N$2:$N$421,'Raw Data'!$H$2:$H$421,B24) -> 76026 | F24: =SUMIFS('Raw Data'!$J$2:$J$421,'Raw Data'!$H$2:$H$421,B24) -> 35

Sheet Product pivot
A2: Row Labels | B2: Sum of Sales | D2: Count of Category | E2: Column Labels
A3: Bookshelf | B3: 355677.49 | D3: Row Labels | E3: Clothing | F3: Electronics | G3: Furniture | H3: Home & Kitchen | I3: Office Supplies
A4: Study Table | B4: 351751.69 | D4: Jan | E4: 4 | F4: 8 | G4: 7 | H4: 8 | I4: 6
A5: Bed Frame | B5: 312388.87 | D5: Feb | E5: 5 | F5: 6 | G5: 6 | H5: 3 | I5: 12
A6: Dinner Set | B6: 288886.33 | D6: Mar | E6: 6 | F6: 8 | G6: 9 | H6: 11 | I6: 5
A7: Vacuum Cleaner | B7: 282782.28 | D7: Apr | E7: 9 | F7: 7 | G7: 4 | H7: 10 | I7: 6
A8: Bean Bag | B8: 252725.73 | D8: May | E8: 11 | F8: 3 | G8: 6 | H8: 8 | I8: 7
A9: Office Chair | B9: 222020.05 | D9: Jun | E9: 9 | F9: 7 | G9: 7 | H9: 11 | I9: 4
A10: USB-C Charger | B10: 206299.55 | D10: Jul | E10: 5 | F10: 4 | G10: 2 | H10: 7 | I10: 8
A11: Table Lamp | B11: 200736.84 | D11: Aug | E11: 11 | F11: 4 | G11: 4 | H11: 5 | I11: 9
A12: Sofa Cover | B12: 198090.86 | D12: Sep | E12: 7 | F12: 5 | G12: 5 | H12: 6 | I12: 9
D13: Oct | E13: 5 | F13: 12 | G13: 4 | H13: 7 | I13: 9
D14: Nov | E14: 12 | F14: 3 | G14: 5 | H14: 6 | I14: 4
A15: Row Labels | B15: Sum of Quantity | D15: Dec | E15: 11 | F15: 8 | G15: 9 | H15: 11 | I15: 10
A16: Clothing | B16: 625
A17: Electronics | B17: 496 | E17: Count of Segment | F17: Column Labels
A18: Furniture | B18: 439 | E18: Row Labels | F18: Consumer | G18: Corporate | H18: Home Office
A19: Home & Kitchen | B19: 635 | E19: Clothing | F19: 52 | G19: 24 | H19: 19
A20: Office Supplies | B20: 569 | E20: Electronics | F20: 42 | G20: 14 | H20: 19
E21: Furniture | F21: 35 | G21: 16 | H21: 17
E22: Home & Kitchen | F22: 48 | G22: 22 | H22: 23
E23: Office Supplies | F23: 48 | G23: 14 | H23: 27
A24: Row Labels | B24: Sum of ShippingCost | C24: Sum of Sales | D24: Sum of Profit
A25: Clothing | B25: 12668.36 | C25: 775337.07 | D25: 211497.56
A26: Electronics | B26: 10673.35 | C26: 1079969 | D26: 286935.47
A27: Furniture | B27: 9255.77 | C27: 2174930.6 | D27: 687192.43
A28: Home & Kitchen | B28: 12426.2 | C28: 1563702.2 | D28: 415643.4
A29: Office Supplies | B29: 12489.3 | C29: 206437.1 | D29: 54896.72

Sheet Product Dashboard
